aind_data_transfer_models/__init__.py
aind_data_transfer_models/core.py
aind_data_transfer_models/s3_upload_configs.py
aind_data_transfer_models/trigger.py
aind_data_transfer_models-0.17.1.dist-info/licenses/LICENSE
aind_data_transfer_models-0.17.1.dist-info/METADATA
aind_data_transfer_models-0.17.1.dist-info/WHEEL
aind_data_transfer_models-0.17.1.dist-info/top_level.txt
aind_data_transfer_models-0.17.1.dist-info/RECORD
