Metadata-Version: 2.4
Name: aind-data-transfer-models
Version: 0.17.1
Summary: Generated from aind-library-template
Author: Allen Institute for Neural Dynamics
License: MIT
Classifier: Programming Language :: Python :: 3
Requires-Python: >=3.9
License-File: LICENSE
Requires-Dist: pydantic>=2.7
Requires-Dist: pydantic-settings>=2.0
Requires-Dist: aind-slurm-rest<0.2.1,>=0.1.0
Requires-Dist: aind-data-schema-models<1.0.0,>=0.3.2
Requires-Dist: email-validator
Requires-Dist: aind-metadata-mapper>=0.18.2
Requires-Dist: aind-codeocean-pipeline-monitor>=0.7.0
Requires-Dist: codeocean
Provides-Extra: dev
Requires-Dist: black; extra == "dev"
Requires-Dist: coverage; extra == "dev"
Requires-Dist: flake8; extra == "dev"
Requires-Dist: interrogate; extra == "dev"
Requires-Dist: isort; extra == "dev"
Requires-Dist: Sphinx; extra == "dev"
Requires-Dist: furo; extra == "dev"
Dynamic: license-file
